filmfestival/main.py
tests/__init__.py
tests/test_integration.py
tests/test_unit.py
filmfestival-0.1.1.dist-info/METADATA
filmfestival-0.1.1.dist-info/WHEEL
filmfestival-0.1.1.dist-info/top_level.txt
filmfestival-0.1.1.dist-info/RECORD
